point2pin
