Metadata-Version: 2.4
Name: point2pin
Version: 0.1.1
Summary: Convert Lat Lng To Indian Pincode
Author-email: Karthik Devan <krtdvn@gmail.com>
Maintainer-email: Karthik Devan <krtdvn@gmail.com>
Project-URL: Homepage, https://github.com/kdqed/point2pin
Project-URL: Issues, https://github.com/kdqed/point2pin/issues
Requires-Python: >=3.12
License-File: LICENSE
Requires-Dist: h3>=4.2.2
Requires-Dist: shapely>=2.1.0
Dynamic: license-file
